maya_umbrella/__init__.py
maya_umbrella/__version__.py
maya_umbrella/_vendor/__init__.py
maya_umbrella/_vendor/atomicwrites/LICENSE
maya_umbrella/_vendor/atomicwrites/__init__.py
maya_umbrella/_vendor/atomicwrites.pyi
maya_umbrella/_vendor/six/__init__.pyi
maya_umbrella/_vendor/six/moves/__init__.pyi
maya_umbrella/_vendor/six/moves/configparser.pyi
maya_umbrella/_vendor/six.LICENSE
maya_umbrella/_vendor/six.py
maya_umbrella/_vendor/vendor.txt
maya_umbrella/cleaner.py
maya_umbrella/collector.py
maya_umbrella/constants.py
maya_umbrella/defender.py
maya_umbrella/filesystem.py
maya_umbrella/hooks/__init__.py
maya_umbrella/hooks/delete_turtle.py
maya_umbrella/hooks/delete_unknown_plugin_node.py
maya_umbrella/hooks/fix_model_panel.py
maya_umbrella/hooks/fix_no_scene_name.py
maya_umbrella/hooks/fix_on_model_change_3dc.py
maya_umbrella/i18n.py
maya_umbrella/locales/en_US.json
maya_umbrella/locales/zh_CN.json
maya_umbrella/log.py
maya_umbrella/maya_funs.py
maya_umbrella/scanner.py
maya_umbrella/signatures.py
maya_umbrella/vaccine.py
maya_umbrella/vaccines/__init__.py
maya_umbrella/vaccines/vaccine1.py
maya_umbrella/vaccines/vaccine2.py
maya_umbrella/vaccines/vaccine3.py
maya_umbrella/vaccines/vaccine4.py
maya_umbrella-0.16.0.dist-info/METADATA
maya_umbrella-0.16.0.dist-info/WHEEL
maya_umbrella-0.16.0.dist-info/licenses/LICENSE
maya_umbrella-0.16.0.dist-info/RECORD
