Metadata-Version: 2.4
Name: maya_umbrella
Version: 0.16.0
Summary: A better Autodesk Maya antivirus tool detects and removes malicious.
License: MIT
License-File: LICENSE
Keywords: Autodesk Maya,python,Maya,dcc,antivirus,Security Tools,maya_umbrella
Author: longhao
Author-email: hal.long@outlook.com
Requires-Python: >=2.7, !=3.0.*, !=3.1.*, !=3.2.*, !=3.3.*, !=3.4.*, !=3.5.*
Classifier: License :: OSI Approved :: MIT License
Classifier: Programming Language :: Python :: 2
Classifier: Programming Language :: Python :: 2.7
Classifier: Programming Language :: Python :: 3
Classifier: Programming Language :: Python :: 3.6
Classifier: Programming Language :: Python :: 3.7
Classifier: Programming Language :: Python :: 3.8
Classifier: Programming Language :: Python :: 3.9
Classifier: Programming Language :: Python :: 3.10
Classifier: Programming Language :: Python :: 3.11
Classifier: Programming Language :: Python :: 3.12
Classifier: Programming Language :: Python :: 3.13
Classifier: Programming Language :: Python :: 3.14
Project-URL: Documentation, https://github.com/loonghao/maya_umbrella
Project-URL: Homepage, https://github.com/loonghao/maya_umbrella
Project-URL: Repository, https://github.com/loonghao/maya_umbrella
